pytest_smtp4dev/__init__.py
pytest_smtp4dev/_version.py
pytest_smtp4dev/client.py
pytest_smtp4dev/models.py
pytest_smtp4dev/plugin.py
pytest_smtp4dev-1.0.0.dist-info/LICENSE
pytest_smtp4dev-1.0.0.dist-info/METADATA
pytest_smtp4dev-1.0.0.dist-info/WHEEL
pytest_smtp4dev-1.0.0.dist-info/entry_points.txt
pytest_smtp4dev-1.0.0.dist-info/top_level.txt
pytest_smtp4dev-1.0.0.dist-info/RECORD
